garpix_utils/MANIFEST.in
garpix_utils/README.md
garpix_utils/__init__.py
garpix_utils/apps.py
garpix_utils/setup.py
garpix_utils/admin/__init__.py
garpix_utils/admin/hideable_fields_mixin.py
garpix_utils/admin/site_configuration.py
garpix_utils/cef_logs/middleware.py
garpix_utils/cef_logs/utils.py
garpix_utils/cef_logs/enums/enums.py
garpix_utils/cef_logs/enums/get_enums.py
garpix_utils/cef_logs/event/__init__.py
garpix_utils/cef_logs/event/base.py
garpix_utils/cef_logs/event/enevts.py
garpix_utils/cef_logs/mixins/__init__.py
garpix_utils/cef_logs/mixins/create_log.py
garpix_utils/cef_logs/mixins/log_admin.py
garpix_utils/cef_logs/mixins/log_admin_solo.py
garpix_utils/decorators/__init__.py
garpix_utils/decorators/extand_enum.py
garpix_utils/file/__init__.py
garpix_utils/file/file_field.py
garpix_utils/file/filepath.py
garpix_utils/logs/__init__.py
garpix_utils/logs/loggers.py
garpix_utils/logs/enums/__init__.py
garpix_utils/logs/enums/action.py
garpix_utils/logs/enums/action_level.py
garpix_utils/logs/enums/action_result.py
garpix_utils/logs/enums/action_type.py
garpix_utils/logs/enums/get_enums.py
garpix_utils/logs/mixins/__init__.py
garpix_utils/logs/mixins/create_log.py
garpix_utils/logs/mixins/log_admin.py
garpix_utils/logs/mixins/log_admin_solo.py
garpix_utils/logs/services/__init__.py
garpix_utils/logs/services/action_element.py
garpix_utils/logs/services/logger_iso.py
garpix_utils/managers/__init__.py
garpix_utils/managers/active_manager.py
garpix_utils/managers/active_on_site_manager.py
garpix_utils/managers/available_manager.py
garpix_utils/managers/current_site_manager.py
garpix_utils/managers/polymorphic_active_manager.py
garpix_utils/managers/polymorphic_available_manager.py
garpix_utils/managers/polymorphic_current_site_manager.py
garpix_utils/models/__init__.py
garpix_utils/models/active_mixin.py
garpix_utils/models/admin_delete_mixin.py
garpix_utils/models/available_mixin.py
garpix_utils/models/delete_mixin.py
garpix_utils/models/empty_mixin.py
garpix_utils-1.11.2.dist-info/METADATA
garpix_utils-1.11.2.dist-info/WHEEL
garpix_utils-1.11.2.dist-info/top_level.txt
garpix_utils-1.11.2.dist-info/RECORD
