Metadata-Version: 2.1
Name: garpix_utils
Version: 1.11.2
Home-page: https://github.com/garpixcms/garpix_utils
Author: Garpix LTD
Author-email: info@garpix.com
License: MIT
Classifier: Development Status :: 4 - Beta
Classifier: Environment :: Web Environment
Classifier: Intended Audience :: Developers
Classifier: License :: OSI Approved :: MIT License
Classifier: Operating System :: OS Independent
Classifier: Programming Language :: Python
Classifier: Framework :: Django
Classifier: Programming Language :: Python :: 3.8
Requires-Dist: Django<5,>=1.11
Requires-Dist: django-uuslug>=1.2.0
Requires-Dist: django-polymorphic-tree-for-garpix-page>=2.2.2
Requires-Dist: djangorestframework>=3.13.0
Requires-Dist: cef-logger>=1.0.0
